README.rst
setup.py
bin/update-waldo
waldo/__init__.py
waldo/retrieve_all.py
waldo/statistics.py
waldo/tools.py
waldo.egg-info/PKG-INFO
waldo.egg-info/SOURCES.txt
waldo.egg-info/dependency_links.txt
waldo.egg-info/requires.txt
waldo.egg-info/top_level.txt
waldo/backend/__init__.py
waldo/backend/backend.py
waldo/go/__init__.py
waldo/go/go.py
waldo/go/load.py
waldo/go/models.py
waldo/goslim/__init__.py
waldo/goslim/goslim.py
waldo/goslim/load.py
waldo/goslim/models.py
waldo/hpa/__init__.py
waldo/hpa/load.py
waldo/hpa/models.py
waldo/hpa/retrieve.py
waldo/locate/__init__.py
waldo/locate/load.py
waldo/locate/models.py
waldo/locate/retrieve.py
waldo/mgi/__init__.py
waldo/mgi/load.py
waldo/mgi/locate.py
waldo/mgi/models.py
waldo/mgi/retrieve.py
waldo/nog/__init__.py
waldo/nog/load.py
waldo/nog/models.py
waldo/nog/retrieve.py
waldo/predictions/__init__.py
waldo/predictions/models.py
waldo/predictions/retrieve.py
waldo/refseq/__init__.py
waldo/refseq/load.py
waldo/sequences/__init__.py
waldo/sequences/fasta.py
waldo/sequences/load.py
waldo/sequences/models.py
waldo/sequences/retrieve.py
waldo/tests/__init__.py
waldo/tests/backend.py
waldo/tests/test_backend.py
waldo/tests/test_clear.py
waldo/tests/test_fasta.py
waldo/tests/test_gen_url.py
waldo/tests/test_go.py
waldo/tests/test_goslim.py
waldo/tests/test_hpa_load.py
waldo/tests/test_hpa_retrieve.py
waldo/tests/test_locate_load.py
waldo/tests/test_locate_retrieve.py
waldo/tests/test_mgi.py
waldo/tests/test_nog_load.py
waldo/tests/test_oop.py
waldo/tests/test_prediction.py
waldo/tests/test_refseq.py
waldo/tests/test_sequences_load.py
waldo/tests/test_statistics.py
waldo/tests/test_translation.py
waldo/tests/test_uniprot.py
waldo/tests/test_uniprot_load.py
waldo/tests/test_uniprot_online.py
waldo/tests/data/LOCATE_human_v6_20081121.xml.zip
waldo/tests/data/LOCATE_mouse_v6_20081121.xml.zip
waldo/tests/data/MRK_ENSEMBL.rpt
waldo/tests/data/MRK_Reference.rpt
waldo/tests/data/Mus_musculus.NCBIM37.60.pep.all.fa.gz
waldo/tests/data/gene2ensembl.gz
waldo/tests/data/gene_association.mgi
waldo/tests/data/gene_ontology.1_2.obo.gz
waldo/tests/data/hpa_annotations.csv
