Metadata-Version: 1.1
Name: waldo
Version: 0.1
Summary: Protein Subcellular Location Information Package
Home-page: http://murphylab.web.cmu.edu/services/waldo/home
Author: Luis Pedro Coelho and others (See AUTHORS.txt file)
Author-email: luis@luispedro.org
License: MIT
Platform: Any
Classifier: Development Status :: 4 - Beta
Classifier: License :: OSI Approved :: MIT License
Classifier: Operating System :: POSIX
Classifier: Operating System :: OS Independent
Classifier: Programming Language :: Python
Classifier: Topic :: Scientific/Engineering
Classifier: Intended Audience :: Science/Research
